pyslog/__init__.py
pyslog/eslog2/__init__.py
pyslog/eslog2/generator.py
pyslog/eslog2/models/__init__.py
pyslog/eslog2/models/_xml.py
pyslog/eslog2/models/enums/__init__.py
pyslog/eslog2/models/enums/allowance_type.py
pyslog/eslog2/models/enums/business_process_type.py
pyslog/eslog2/models/enums/item_identification_scheme.py
pyslog/eslog2/models/enums/payment_means_code.py
pyslog/eslog2/models/enums/vat_category_code.py
pyslog/eslog2/models/enums/vat_point_date_code.py
pyslog/eslog2/models/invoice.py
pyslog/eslog2/schemas/eSLOG20_INVOIC_v200.xsd
pyslog/eslog2/validator.py
pyslog-0.1.0.dev16.dist-info/WHEEL
pyslog-0.1.0.dev16.dist-info/METADATA
pyslog-0.1.0.dev16.dist-info/RECORD
