Metadata-Version: 2.4
Name: pyslog
Version: 0.1.0.dev16
Summary: Python e-SLOG library. Simplifies the generation of Slovenian e-SLOG electronic documents.
Keywords: eslog,eracun,e-racun,e-invoice
Author: Gregor Gabrovšek
License-Expression: MIT
Classifier: Development Status :: 3 - Alpha
Classifier: Framework :: Pydantic
Classifier: Framework :: Pydantic :: 2
Classifier: Intended Audience :: Developers
Classifier: License :: OSI Approved :: MIT License
Classifier: Operating System :: OS Independent
Classifier: Programming Language :: Python :: 3
Classifier: Programming Language :: Python :: 3 :: Only
Classifier: Programming Language :: Python :: 3.10
Classifier: Programming Language :: Python :: 3.11
Classifier: Programming Language :: Python :: 3.12
Classifier: Programming Language :: Python :: 3.13
Classifier: Topic :: Software Development :: Libraries :: Python Modules
Classifier: Topic :: Office/Business
Classifier: Topic :: Text Processing :: Markup :: XML
Classifier: Typing :: Typed
Requires-Dist: pydantic~=2.12.5
Requires-Dist: lxml~=6.0.2
Requires-Dist: pydantic-xml~=2.18.0
Maintainer: Gregor Gabrovšek
Requires-Python: >=3.10
Project-URL: Repository, https://github.com/gregorgabrovsek/pyslog
